README.md
setup.cfg
setup.py
pmodel/__version__.py
pmodel/utils.py
pmodel.egg-info/PKG-INFO
pmodel.egg-info/SOURCES.txt
pmodel.egg-info/dependency_links.txt
pmodel.egg-info/requires.txt
pmodel.egg-info/top_level.txt