Metadata-Version: 2.1
Name: pmodel
Version: 0.0.2
Summary: Translate of algorithm p-Model from Matlab to Python Package. Original algorithm avaiable at http://www2.meteo.uni-bonn.de/staff/venema/themes/surrogates/pmodel/pmodel.m
Home-page: https://adrianopereira.github.io
Author: Adriano P. Almeida
Author-email: adriano.almeida@inpe.br
License: MIT
Platform: UNKNOWN
Requires-Python: !=3.0.*, !=3.1.*, !=3.2.*, !=3.3.*
